{
    "name": "cloudiot",
    "name_pretty": "Google Cloud Internet of Things (IoT) Core",
    "product_documentation": "https://cloud.google.com/iot",
    "client_documentation": "https://cloud.google.com/python/docs/reference/cloudiot/latest",
    "issue_tracker": "https://issuetracker.google.com/issues?q=status:open%20componentid:310170",
    "release_level": "stable",
    "language": "python",
    "library_type": "GAPIC_AUTO",
    "repo": "googleapis/python-iot",
    "distribution_name": "google-cloud-iot",
    "api_id": "cloudiot.googleapis.com",
    "requires_billing": true,
    "default_version": "v1",
    "codeowner_team": "@googleapis/api-iot",
    "api_shortname": "cloudiot",
    "api_description": "is a complete set of tools to connect, process, store, and analyze data both at the edge and in the cloud. The platform consists of scalable, fully-managed cloud services; an integrated software stack for edge/on-premises computing with machine learning capabilities for all your IoT needs."
}
